{
  "data": {
    "article": {},
    "attachments": {},
    "author_id": "2043745937298792448",
    "conversation_id": "2074297112880390544",
    "created_at": "2026-07-07T05:44:33.000Z",
    "edit_controls": {
      "editable_until": "2026-07-07T06:44:33.000Z",
      "edits_remaining": 5,
      "is_edit_eligible": false
    },
    "edit_history_tweet_ids": [
      "2074368953540071905"
    ],
    "entities": {
      "mentions": [
        {
          "end": 8,
          "id": "2055263152238198784",
          "start": 0,
          "username": "Reiau9e"
        }
      ]
    },
    "geo": {},
    "id": "2074368953540071905",
    "in_reply_to_user_id": "2055263152238198784",
    "lang": "zh",
    "note_tweet": {
      "entities": {}
    },
    "possibly_sensitive": false,
    "public_metrics": {
      "bookmark_count": 0,
      "impression_count": 0,
      "like_count": 0,
      "quote_count": 0,
      "reply_count": 0,
      "retweet_count": 0
    },
    "referenced_tweets": [
      {
        "id": "2074297112880390544",
        "type": "replied_to"
      }
    ],
    "reply_settings": "everyone",
    "text": "@Reiau9e 小哥小哥，这个腿身比头身比是怎么做到的🥺🥺"
  },
  "includes": {
    "media": [
      {
        "height": 2048,
        "media_key": "3_2074297106601508865",
        "public_metrics": {},
        "type": "photo",
        "url": "https://pbs.twimg.com/media/HMliOnWagAEs7z0.jpg",
        "width": 1538
      }
    ],
    "tweets": [
      {
        "article": {},
        "attachments": {},
        "author_id": "2043745937298792448",
        "conversation_id": "2074297112880390544",
        "created_at": "2026-07-07T05:44:33.000Z",
        "edit_controls": {
          "editable_until": "2026-07-07T06:44:33.000Z",
          "edits_remaining": 5,
          "is_edit_eligible": false
        },
        "edit_history_tweet_ids": [
          "2074368953540071905"
        ],
        "entities": {
          "mentions": [
            {
              "end": 8,
              "id": "2055263152238198784",
              "start": 0,
              "username": "Reiau9e"
            }
          ]
        },
        "geo": {},
        "id": "2074368953540071905",
        "in_reply_to_user_id": "2055263152238198784",
        "lang": "zh",
        "note_tweet": {
          "entities": {}
        },
        "possibly_sensitive": false,
        "public_metrics": {
          "bookmark_count": 0,
          "impression_count": 0,
          "like_count": 0,
          "quote_count": 0,
          "reply_count": 0,
          "retweet_count": 0
        },
        "referenced_tweets": [
          {
            "id": "2074297112880390544",
            "type": "replied_to"
          }
        ],
        "reply_settings": "everyone",
        "text": "@Reiau9e 小哥小哥，这个腿身比头身比是怎么做到的🥺🥺"
      },
      {
        "article": {},
        "attachments": {
          "media_keys": [
            "3_2074297106601508865"
          ]
        },
        "author_id": "2055263152238198784",
        "conversation_id": "2074297112880390544",
        "created_at": "2026-07-07T00:59:04.000Z",
        "edit_controls": {
          "editable_until": "2026-07-07T01:59:04.000Z",
          "edits_remaining": 5,
          "is_edit_eligible": true
        },
        "edit_history_tweet_ids": [
          "2074297112880390544"
        ],
        "entities": {
          "urls": [
            {
              "display_url": "pic.x.com/LD4suJ3rsb",
              "end": 36,
              "expanded_url": "https://x.com/Reiau9e/status/2074297112880390544/photo/1",
              "media_key": "3_2074297106601508865",
              "start": 13,
              "url": "https://t.co/LD4suJ3rsb"
            }
          ]
        },
        "geo": {},
        "id": "2074297112880390544",
        "lang": "zh",
        "note_tweet": {
          "entities": {}
        },
        "possibly_sensitive": false,
        "public_metrics": {
          "bookmark_count": 0,
          "impression_count": 846,
          "like_count": 30,
          "quote_count": 0,
          "reply_count": 8,
          "retweet_count": 0
        },
        "reply_settings": "everyone",
        "text": "试一试藏袍但还是有点太大 https://t.co/LD4suJ3rsb"
      }
    ],
    "users": [
      {
        "created_at": "2026-04-13T17:39:53.000Z",
        "description": "戒药戒毒戒推❌💊💉\n三戒保平安🙏🏻🙏🏻🙏🏻\n减害大法好🗿🗿🌞",
        "id": "2043745937298792448",
        "location": "乌鲁木齐中路",
        "name": "超级伊伊伊万#忒伊亚",
        "pinned_tweet_id": "2070001259625779694",
        "profile_image_url": "https://pbs.twimg.com/profile_images/2052144771750301696/N6iJMxi6_normal.jpg",
        "protected": false,
        "public_metrics": {
          "followers_count": 129,
          "following_count": 127,
          "like_count": 1955,
          "listed_count": 0,
          "media_count": 26,
          "tweet_count": 193
        },
        "url": "",
        "username": "ivan20221126",
        "verified": false
      },
      {
        "created_at": "2026-05-15T12:25:25.000Z",
        "description": "保卫胡言乱语",
        "id": "2055263152238198784",
        "name": "rei",
        "profile_image_url": "https://pbs.twimg.com/profile_images/2061638515864346625/3yEXkh-c_normal.jpg",
        "protected": false,
        "public_metrics": {
          "followers_count": 780,
          "following_count": 731,
          "like_count": 7527,
          "listed_count": 1,
          "media_count": 3,
          "tweet_count": 55
        },
        "url": "",
        "username": "Reiau9e",
        "verified": false
      }
    ]
  }
}